fAES.py
fAES-1.0.0.dist-info/METADATA
fAES-1.0.0.dist-info/WHEEL
fAES-1.0.0.dist-info/top_level.txt
fAES-1.0.0.dist-info/RECORD
